cachegrab/__init__.py
cachegrab/decorators.py
cachegrab/utils.py
cachegrab-0.2.2.dist-info/LICENSE
cachegrab-0.2.2.dist-info/METADATA
cachegrab-0.2.2.dist-info/WHEEL
cachegrab-0.2.2.dist-info/RECORD
