Metadata-Version: 2.1
Name: cachegrab
Version: 0.2.2
Summary: Decorators for caching instance methods.
Home-page: https://github.com/zteinck/cachegrab
License: MIT
Author: Zachary Einck
Author-email: zacharyeinck@gmail.com
Requires-Python: >=3.8,<4.0
Classifier: License :: OSI Approved :: MIT License
Classifier: Programming Language :: Python :: 3
Classifier: Programming Language :: Python :: 3.8
Classifier: Programming Language :: Python :: 3.9
Classifier: Programming Language :: Python :: 3.10
Classifier: Programming Language :: Python :: 3.11
Classifier: Programming Language :: Python :: 3.12
Requires-Dist: pandas
Project-URL: Repository, https://github.com/zteinck/cachegrab
